atlas_consortia_commons/__init__.py
atlas_consortia_commons/converter/__init__.py
atlas_consortia_commons/decorator/__init__.py
atlas_consortia_commons/file/__init__.py
atlas_consortia_commons/object/__init__.py
atlas_consortia_commons/rest/__init__.py
atlas_consortia_commons/string/__init__.py
atlas_consortia_commons/ubkg/__init__.py
atlas_consortia_commons/ubkg/ubkg_sdk.py
atlas_consortia_commons/url/__init__.py
atlas_consortia_commons-1.1.6.dist-info/METADATA
atlas_consortia_commons-1.1.6.dist-info/WHEEL
atlas_consortia_commons-1.1.6.dist-info/top_level.txt
atlas_consortia_commons-1.1.6.dist-info/RECORD
