Metadata-Version: 2.4
Name: atlas_consortia_commons
Version: 1.1.6
Summary: The common code supporting the web services in the consortia.
Home-page: https://github.com/x-atlas-consortia/commons
Author: Atlas Consortia
Author-email: api-developers@hubmapconsortium.org
Classifier: Programming Language :: Python :: 3
Classifier: Operating System :: OS Independent
Requires-Python: >=3.6
Requires-Dist: Flask>=3.0.3
Requires-Dist: Werkzeug>=3.0.3
Requires-Dist: hubmap-commons>=2.1.18
Requires-Dist: jsonref==0.3.0
Requires-Dist: jsonschema>=3.2.0
Requires-Dist: neo4j>=5.20.0
Requires-Dist: pytz>=2021.1
Requires-Dist: property>=2.2
Requires-Dist: globus_sdk>=2.0.1
Requires-Dist: prov>=1.5.1
Requires-Dist: requests>=2.32.3
Requires-Dist: PyYAML>=6.0
Dynamic: author
Dynamic: author-email
Dynamic: classifier
Dynamic: description
Dynamic: description-content-type
Dynamic: home-page
Dynamic: requires-dist
Dynamic: requires-python
Dynamic: summary
